LICENSE
st_compat/__init__.py
st_compat/runtime/__init__.py
st_compat/runtime/scriptrunner.py
st_compat/version.py
st_compat-0.0.1a2.dist-info/WHEEL
st_compat-0.0.1a2.dist-info/LICENSE
st_compat-0.0.1a2.dist-info/METADATA
st_compat-0.0.1a2.dist-info/RECORD
